uart_tx_module.v

`timescale 1ns/1ps
// -----------------------------------------------------------------------------
// UART Transmitter 8-N-1
// Transmits LSB first. Parameterizable CLKS_PER_BIT = Fclk / Baud.
// Example for sim: with clk=50MHz and baud=115200 -> ~434; but for faster
// simulation you can pick a small value (default 16).
// -----------------------------------------------------------------------------
module uart_tx_module
#(
    parameter integer CLKS_PER_BIT = 16  // clocks per bit
)
(
    input  wire clk,
    input  wire rst_n,       // active-low async reset (tie high if unused)
    input  wire start,       // pulse '1' at least 1 clk to start sending "data"
    input  wire [7:0] data,  // byte to send
    output reg  tx,          // serial line (idles at '1')
    output reg  busy         // 1 while transmitting
);

    // FSM states
    localparam [2:0]
        S_IDLE  = 3'd0,
        S_START = 3'd1,
        S_DATA  = 3'd2,
        S_STOP  = 3'd3;

    reg [2:0]  state = S_IDLE;
    reg [3:0]  bit_idx;                  // 0..7
    reg [7:0]  shifter;
    reg [15:0] clk_cnt;                  // supports CLKS_PER_BIT up to 65535

    // TX idles high
    initial begin
        tx   = 1'b1;
        busy = 1'b0;
    end

    wire tick = (clk_cnt == CLKS_PER_BIT-1);

    always @(posedge clk or negedge rst_n) begin
        if (!rst_n) begin
            state   <= S_IDLE;
            tx      <= 1'b1;
            busy    <= 1'b0;
            bit_idx <= 4'd0;
            clk_cnt <= 16'd0;
            shifter <= 8'd0;
        end else begin
            case (state)
                S_IDLE: begin
                    tx   <= 1'b1;
                    busy <= 1'b0;
                    clk_cnt <= 0;
                    if (start) begin
                        busy    <= 1'b1;
                        shifter <= data;
                        bit_idx <= 0;
                        state   <= S_START;
                        tx      <= 1'b0;        // start bit
                    end
                end

                S_START: begin
                    // hold start bit for one bit time
                    if (tick) begin
                        clk_cnt <= 0;
                        state   <= S_DATA;
                        tx      <= shifter[0];  // first data bit (LSB)
                    end else begin
                        clk_cnt <= clk_cnt + 1;
                    end
                end

                S_DATA: begin
                    if (tick) begin
                        clk_cnt <= 0;
                        bit_idx <= bit_idx + 1;
                        shifter <= {1'b0, shifter[7:1]}; // shift right
                        if (bit_idx == 4'd7) begin
                            state <= S_STOP;
                            tx    <= 1'b1;      // stop bit
                        end else begin
                            tx    <= shifter[1]; // next bit after shift
                        end
                    end else begin
                        clk_cnt <= clk_cnt + 1;
                    end
                end

                S_STOP: begin
                    if (tick) begin
                        clk_cnt <= 0;
                        state   <= S_IDLE;
                        busy    <= 1'b0;
                        tx      <= 1'b1;        // line back to idle
                    end else begin
                        clk_cnt <= clk_cnt + 1;
                    end
                end

                default: state <= S_IDLE;
            endcase
        end
    end

endmodule

uart_rx_module.v
`timescale 1ns/1ps
// -----------------------------------------------------------------------------
// UART Receiver 8-N-1
// Recibe LSB primero. Parameterizable CLKS_PER_BIT = Fclk / Baud.
// Ejemplo: clk=50MHz, baud=115200 → ~434
// -----------------------------------------------------------------------------
module uart_rx_module
#(
    parameter integer CLKS_PER_BIT = 16  // clocks per bit
)
(
    input  wire clk,
    input  wire rst_n,       // reset asincrónico activo en bajo
    input  wire rx,          // línea serial de entrada
    output reg  [7:0] data,  // byte recibido
    output reg  ready        // pulso 1 clk cuando se recibió un byte
);

    // FSM states
    localparam [2:0]
        S_IDLE   = 3'd0,
        S_START  = 3'd1,
        S_DATA   = 3'd2,
        S_STOP   = 3'd3;

    reg [2:0]  state = S_IDLE;
    reg [3:0]  bit_idx;       // 0..7
    reg [7:0]  data_buf;
    reg [15:0] clk_cnt;       // cuenta hasta CLKS_PER_BIT
    reg        rx_sync0, rx_sync1;  // sincronizar rx con clk

    // Sincronizar rx a clk (para evitar metastabilidad)
    always @(posedge clk or negedge rst_n) begin
        if (!rst_n) begin
            rx_sync0 <= 1'b1;
            rx_sync1 <= 1'b1;
        end else begin
            rx_sync0 <= rx;
            rx_sync1 <= rx_sync0;
        end
    end

    wire rx_clean = rx_sync1;

    // RX FSM
    always @(posedge clk or negedge rst_n) begin
        if (!rst_n) begin
            state    <= S_IDLE;
            clk_cnt  <= 0;
            bit_idx  <= 0;
            data_buf <= 0;
            data     <= 0;
            ready    <= 0;
        end else begin
            ready <= 0;  // default (solo se pone 1 un ciclo)
            case (state)
                // Esperando start bit
                S_IDLE: begin
                    if (rx_clean == 1'b0) begin  // detecta transición a 0
                        state   <= S_START;
                        clk_cnt <= 0;
                    end
                end

                // Mitad del start bit (para centrar muestreo)
                S_START: begin
                    if (clk_cnt == (CLKS_PER_BIT/2)) begin
                        if (rx_clean == 1'b0) begin
                            clk_cnt <= 0;
                            bit_idx <= 0;
                            state   <= S_DATA;
                        end else begin
                            state <= S_IDLE; // falso start
                        end
                    end else begin
                        clk_cnt <= clk_cnt + 1;
                    end
                end

                // Recepción de los 8 bits
                S_DATA: begin
                    if (clk_cnt == CLKS_PER_BIT-1) begin
                        clk_cnt <= 0;
                        data_buf[bit_idx] <= rx_clean;
                        if (bit_idx == 7) begin
                            state <= S_STOP;
                        end else begin
                            bit_idx <= bit_idx + 1;
                        end
                    end else begin
                        clk_cnt <= clk_cnt + 1;
                    end
                end

                // Stop bit
                S_STOP: begin
                    if (clk_cnt == CLKS_PER_BIT-1) begin
                        state   <= S_IDLE;
                        clk_cnt <= 0;
                        data    <= data_buf;
                        ready   <= 1;   // indicar byte válido
                    end else begin
                        clk_cnt <= clk_cnt + 1;
                    end
                end

                default: state <= S_IDLE;
            endcase
        end
    end

endmodule

io_interface.v


`timescale 1ns/1ps


// -----------------------------------------------------------------------------
// I/O interface: maps switches->leds and exposes UART RX/TX
// -----------------------------------------------------------------------------
module io_interface
#(
    parameter integer CLKS_PER_BIT = 434   // para clk=50MHz y baud=115200
)
(
    input  wire        clk,        // reloj de 50 MHz
    input  wire        rst_n,      // reset activo en bajo
    input  wire [7:0]  switches,   // 8 switches
    output reg  [7:0]  leds,       // 8 LEDs
    input  wire        uart_rx,    // UART RX desde PC
    output wire        uart_tx     // UART TX hacia PC
);

    // ------------------------
    // Señales UART RX/TX
    // ------------------------
    wire [7:0] rx_data;
    wire       rx_ready;
    reg  [7:0] tx_data;
    reg        tx_start;
    wire       tx_busy;

    // ------------------------
    // Lógica LEDs: actualiza solo cuando llega dato nuevo por UART
    // ------------------------
    always @(posedge clk or negedge rst_n) begin
        if (!rst_n) begin
            leds <= 8'b00000000;
        end else if (rx_ready) begin
            leds <= switches | rx_data;
        end else begin
            leds <= switches;
        end
    end

    // ------------------------
    // Enviar switches por UART (pulso de tx_start de varios ciclos)
    // ------------------------
    reg [2:0] tx_start_cnt;

    always @(posedge clk or negedge rst_n) begin
        if (!rst_n) begin
            tx_start_cnt <= 3'd0;
            tx_start     <= 1'b0;
            tx_data      <= 8'h00;
        end else if (!tx_busy && tx_start_cnt == 3'd0) begin
            tx_data      <= switches;
            tx_start     <= 1'b1;
            tx_start_cnt <= 3'd4; // duración del pulso: 4 ciclos
        end else if (tx_start_cnt > 0) begin
            tx_start     <= 1'b1;
            tx_start_cnt <= tx_start_cnt - 1;
        end else begin
            tx_start     <= 1'b0;
        end
    end

    // ------------------------
    // Instancia del UART RX
    // ------------------------
    uart_rx_module #(
        .CLKS_PER_BIT(CLKS_PER_BIT)
    ) U_RX (
        .clk(clk),
        .rst_n(rst_n),
        .rx(uart_rx),
        .data(rx_data),
        .ready(rx_ready)
    );

    // ------------------------
    // Instancia del UART TX
    // ------------------------
    uart_tx_module #(
        .CLKS_PER_BIT(CLKS_PER_BIT)
    ) U_TX (
        .clk(clk),
        .rst_n(rst_n),
        .start(tx_start),
        .data(tx_data),
        .tx(uart_tx),
        .busy(tx_busy)
    );

endmodule

tb_io_interface.v
`timescale 1ns/1ps
`include "io_interface.v"
`include "uart_rx_module.v"
`include "uart_tx_module.v"
module tb_io_interface;
    // Clock: 50 MHz -> 20 ns period
    reg clk = 0;
    always #10 clk = ~clk;

    reg rst_n = 0;
    reg [7:0] switches = 8'h00;
    wire [7:0] leds;
    reg        uart_rx = 1'b1; // UART idle is high
    wire       uart_tx;

    // Instancia del DUT
    io_interface dut (
        .clk      (clk),
        .rst_n    (rst_n),
        .switches (switches),
        .leds     (leds),
        .uart_rx  (uart_rx),
        .uart_tx  (uart_tx)
    );

    // VCD dump
    initial begin
        $dumpfile("io_interface.vcd");
        $dumpvars(0, tb_io_interface);
    end

    // Estímulos
    initial begin
        // Reset
        rst_n = 0;
        repeat (3) @(posedge clk);
        rst_n = 1;

        // Cambiar switches (deberían reflejarse en los LEDs)
        switches = 8'b1010_1100;
        repeat (10) @(posedge clk);
        switches = 8'b0101_0011;
        repeat (10) @(posedge clk);

        // Simular recepción UART de un byte (ejemplo: 0x55)
        uart_rx_byte(8'h55);

        repeat (20) @(posedge clk);

        $finish;
    end

    // Tarea para simular la recepción UART
    task uart_rx_byte(input [7:0] data);
        integer i;
        begin
            // Start bit
            uart_rx = 1'b0;
            repeat (16) @(posedge clk); // CLKS_PER_BIT = 16

            // Data bits (LSB first)
            for (i = 0; i < 8; i = i + 1) begin
                uart_rx = data[i];
                repeat (16) @(posedge clk);
            end

            // Stop bit
            uart_rx = 1'b1;
            repeat (16) @(posedge clk);
        end
    endtask

endmodule

io_interface.vcd
$date
	Sun Sep  7 20:31:28 2025
$end
$version
	Icarus Verilog
$end
$timescale
	1ps
$end
$scope module tb_io_interface $end
$var wire 1 ! uart_tx $end
$var wire 8 " leds [7:0] $end
$var reg 1 # clk $end
$var reg 1 $ rst_n $end
$var reg 8 % switches [7:0] $end
$var reg 1 & uart_rx $end
$scope module dut $end
$var wire 1 # clk $end
$var wire 1 $ rst_n $end
$var wire 8 ' switches [7:0] $end
$var wire 1 & uart_rx $end
$var wire 1 ! uart_tx $end
$var wire 1 ( tx_busy $end
$var wire 1 ) rx_ready $end
$var wire 8 * rx_data [7:0] $end
$var parameter 32 + CLKS_PER_BIT $end
$var reg 8 , leds [7:0] $end
$var reg 8 - tx_data [7:0] $end
$var reg 1 . tx_start $end
$var reg 3 / tx_start_cnt [2:0] $end
$scope module U_RX $end
$var wire 1 # clk $end
$var wire 1 $ rst_n $end
$var wire 1 & rx $end
$var wire 1 0 rx_clean $end
$var parameter 32 1 CLKS_PER_BIT $end
$var parameter 3 2 S_DATA $end
$var parameter 3 3 S_IDLE $end
$var parameter 3 4 S_START $end
$var parameter 3 5 S_STOP $end
$var reg 4 6 bit_idx [3:0] $end
$var reg 16 7 clk_cnt [15:0] $end
$var reg 8 8 data [7:0] $end
$var reg 8 9 data_buf [7:0] $end
$var reg 1 ) ready $end
$var reg 1 : rx_sync0 $end
$var reg 1 ; rx_sync1 $end
$var reg 3 < state [2:0] $end
$upscope $end
$scope module U_TX $end
$var wire 1 # clk $end
$var wire 8 = data [7:0] $end
$var wire 1 $ rst_n $end
$var wire 1 . start $end
$var wire 1 > tick $end
$var parameter 32 ? CLKS_PER_BIT $end
$var parameter 3 @ S_DATA $end
$var parameter 3 A S_IDLE $end
$var parameter 3 B S_START $end
$var parameter 3 C S_STOP $end
$var reg 4 D bit_idx [3:0] $end
$var reg 1 ( busy $end
$var reg 16 E clk_cnt [15:0] $end
$var reg 8 F shifter [7:0] $end
$var reg 3 G state [2:0] $end
$var reg 1 ! tx $end
$upscope $end
$upscope $end
$scope task uart_rx_byte $end
$var reg 8 H data [7:0] $end
$var integer 32 I i [31:0] $end
$upscope $end
$upscope $end
$enddefinitions $end
$comment Show the parameter values. $end
$dumpall
b11 C
b1 B
b0 A
b10 @
b110110010 ?
b11 5
b1 4
b0 3
b10 2
b110110010 1
b110110010 +
$end
#0
$dumpvars
bx I
bx H
b0 G
b0 F
b0 E
b0 D
0>
b0 =
b0 <
1;
1:
b0 9
b0 8
b0 7
b0 6
10
b0 /
0.
b0 -
b0 ,
b0 *
0)
0(
b0 '
1&
b0 %
0$
0#
b0 "
1!
$end
#10000
1#
#20000
0#
#30000
1#
#40000
0#
#50000
b100 /
1.
b10101100 -
b10101100 =
b10101100 "
b10101100 ,
b10101100 %
b10101100 '
1$
1#
#60000
0#
#70000
0!
b1 G
b10101100 F
1(
b11 /
1#
#80000
0#
#90000
b10 /
b1 E
1#
#100000
0#
#110000
b10 E
b1 /
1#
#120000
0#
#130000
b0 /
b11 E
1#
#140000
0#
#150000
b100 E
0.
1#
#160000
0#
#170000
b101 E
1#
#180000
0#
#190000
b110 E
1#
#200000
0#
#210000
b111 E
1#
#220000
0#
#230000
b1000 E
1#
#240000
0#
#250000
b1010011 "
b1010011 ,
b1001 E
b1010011 %
b1010011 '
1#
#260000
0#
#270000
b1010 E
1#
#280000
0#
#290000
b1011 E
1#
#300000
0#
#310000
b1100 E
1#
#320000
0#
#330000
b1101 E
1#
#340000
0#
#350000
b1110 E
1#
#360000
0#
#370000
b1111 E
1#
#380000
0#
#390000
b10000 E
1#
#400000
0#
#410000
b10001 E
1#
#420000
0#
#430000
b10010 E
1#
#440000
0#
#450000
b10011 E
0:
0&
b1010101 H
1#
#460000
0#
#470000
00
0;
b10100 E
1#
#480000
0#
#490000
b10101 E
b1 <
1#
#500000
0#
#510000
b1 7
b10110 E
1#
#520000
0#
#530000
b10111 E
b10 7
1#
#540000
0#
#550000
b11 7
b11000 E
1#
#560000
0#
#570000
b11001 E
b100 7
1#
#580000
0#
#590000
b101 7
b11010 E
1#
#600000
0#
#610000
b11011 E
b110 7
1#
#620000
0#
#630000
b111 7
b11100 E
1#
#640000
0#
#650000
b11101 E
b1000 7
1#
#660000
0#
#670000
b1001 7
b11110 E
1#
#680000
0#
#690000
b11111 E
b1010 7
1#
#700000
0#
#710000
b1011 7
b100000 E
1#
#720000
0#
#730000
b100001 E
b1100 7
1#
#740000
0#
#750000
b1101 7
b100010 E
1#
#760000
0#
#770000
b100011 E
b1110 7
1:
1&
b0 I
1#
#780000
0#
#790000
10
1;
b1111 7
b100100 E
1#
#800000
0#
#810000
b100101 E
b10000 7
1#
#820000
0#
#830000
b10001 7
b100110 E
1#
#840000
0#
#850000
b100111 E
b10010 7
1#
#860000
0#
#870000
b10011 7
b101000 E
1#
#880000
0#
#890000
b101001 E
b10100 7
1#
#900000
0#
#910000
b10101 7
b101010 E
1#
#920000
0#
#930000
b101011 E
b10110 7
1#
#940000
0#
#950000
b10111 7
b101100 E
1#
#960000
0#
#970000
b101101 E
b11000 7
1#
#980000
0#
#990000
b11001 7
b101110 E
1#
#1000000
0#
#1010000
b101111 E
b11010 7
1#
#1020000
0#
#1030000
b11011 7
b110000 E
1#
#1040000
0#
#1050000
b110001 E
b11100 7
1#
#1060000
0#
#1070000
b11101 7
b110010 E
1#
#1080000
0#
#1090000
b110011 E
b11110 7
0:
0&
b1 I
1#
#1100000
0#
#1110000
00
0;
b11111 7
b110100 E
1#
#1120000
0#
#1130000
b110101 E
b100000 7
1#
#1140000
0#
#1150000
b100001 7
b110110 E
1#
#1160000
0#
#1170000
b110111 E
b100010 7
1#
#1180000
0#
#1190000
b100011 7
b111000 E
1#
#1200000
0#
#1210000
b111001 E
b100100 7
1#
#1220000
0#
#1230000
b100101 7
b111010 E
1#
#1240000
0#
#1250000
b111011 E
b100110 7
1#
#1260000
0#
#1270000
b100111 7
b111100 E
1#
#1280000
0#
#1290000
b111101 E
b101000 7
1#
#1300000
0#
#1310000
b101001 7
b111110 E
1#
#1320000
0#
#1330000
b111111 E
b101010 7
1#
#1340000
0#
#1350000
b101011 7
b1000000 E
1#
#1360000
0#
#1370000
b1000001 E
b101100 7
1#
#1380000
0#
#1390000
b101101 7
b1000010 E
1#
#1400000
0#
#1410000
b1000011 E
b101110 7
1:
1&
b10 I
1#
#1420000
0#
#1430000
10
1;
b101111 7
b1000100 E
1#
#1440000
0#
#1450000
b1000101 E
b110000 7
1#
#1460000
0#
#1470000
b110001 7
b1000110 E
1#
#1480000
0#
#1490000
b1000111 E
b110010 7
1#
#1500000
0#
#1510000
b110011 7
b1001000 E
1#
#1520000
0#
#1530000
b1001001 E
b110100 7
1#
#1540000
0#
#1550000
b110101 7
b1001010 E
1#
#1560000
0#
#1570000
b1001011 E
b110110 7
1#
#1580000
0#
#1590000
b110111 7
b1001100 E
1#
#1600000
0#
#1610000
b1001101 E
b111000 7
1#
#1620000
0#
#1630000
b111001 7
b1001110 E
1#
#1640000
0#
#1650000
b1001111 E
b111010 7
1#
#1660000
0#
#1670000
b111011 7
b1010000 E
1#
#1680000
0#
#1690000
b1010001 E
b111100 7
1#
#1700000
0#
#1710000
b111101 7
b1010010 E
1#
#1720000
0#
#1730000
b1010011 E
b111110 7
0:
0&
b11 I
1#
#1740000
0#
#1750000
00
0;
b111111 7
b1010100 E
1#
#1760000
0#
#1770000
b1010101 E
b1000000 7
1#
#1780000
0#
#1790000
b1000001 7
b1010110 E
1#
#1800000
0#
#1810000
b1010111 E
b1000010 7
1#
#1820000
0#
#1830000
b1000011 7
b1011000 E
1#
#1840000
0#
#1850000
b1011001 E
b1000100 7
1#
#1860000
0#
#1870000
b1000101 7
b1011010 E
1#
#1880000
0#
#1890000
b1011011 E
b1000110 7
1#
#1900000
0#
#1910000
b1000111 7
b1011100 E
1#
#1920000
0#
#1930000
b1011101 E
b1001000 7
1#
#1940000
0#
#1950000
b1001001 7
b1011110 E
1#
#1960000
0#
#1970000
b1011111 E
b1001010 7
1#
#1980000
0#
#1990000
b1001011 7
b1100000 E
1#
#2000000
0#
#2010000
b1100001 E
b1001100 7
1#
#2020000
0#
#2030000
b1001101 7
b1100010 E
1#
#2040000
0#
#2050000
b1100011 E
b1001110 7
1:
1&
b100 I
1#
#2060000
0#
#2070000
10
1;
b1001111 7
b1100100 E
1#
#2080000
0#
#2090000
b1100101 E
b1010000 7
1#
#2100000
0#
#2110000
b1010001 7
b1100110 E
1#
#2120000
0#
#2130000
b1100111 E
b1010010 7
1#
#2140000
0#
#2150000
b1010011 7
b1101000 E
1#
#2160000
0#
#2170000
b1101001 E
b1010100 7
1#
#2180000
0#
#2190000
b1010101 7
b1101010 E
1#
#2200000
0#
#2210000
b1101011 E
b1010110 7
1#
#2220000
0#
#2230000
b1010111 7
b1101100 E
1#
#2240000
0#
#2250000
b1101101 E
b1011000 7
1#
#2260000
0#
#2270000
b1011001 7
b1101110 E
1#
#2280000
0#
#2290000
b1101111 E
b1011010 7
1#
#2300000
0#
#2310000
b1011011 7
b1110000 E
1#
#2320000
0#
#2330000
b1110001 E
b1011100 7
1#
#2340000
0#
#2350000
b1011101 7
b1110010 E
1#
#2360000
0#
#2370000
b1110011 E
b1011110 7
0:
0&
b101 I
1#
#2380000
0#
#2390000
00
0;
b1011111 7
b1110100 E
1#
#2400000
0#
#2410000
b1110101 E
b1100000 7
1#
#2420000
0#
#2430000
b1100001 7
b1110110 E
1#
#2440000
0#
#2450000
b1110111 E
b1100010 7
1#
#2460000
0#
#2470000
b1100011 7
b1111000 E
1#
#2480000
0#
#2490000
b1111001 E
b1100100 7
1#
#2500000
0#
#2510000
b1100101 7
b1111010 E
1#
#2520000
0#
#2530000
b1111011 E
b1100110 7
1#
#2540000
0#
#2550000
b1100111 7
b1111100 E
1#
#2560000
0#
#2570000
b1111101 E
b1101000 7
1#
#2580000
0#
#2590000
b1101001 7
b1111110 E
1#
#2600000
0#
#2610000
b1111111 E
b1101010 7
1#
#2620000
0#
#2630000
b1101011 7
b10000000 E
1#
#2640000
0#
#2650000
b10000001 E
b1101100 7
1#
#2660000
0#
#2670000
b1101101 7
b10000010 E
1#
#2680000
0#
#2690000
b10000011 E
b1101110 7
1:
1&
b110 I
1#
#2700000
0#
#2710000
10
1;
b1101111 7
b10000100 E
1#
#2720000
0#
#2730000
b10000101 E
b1110000 7
1#
#2740000
0#
#2750000
b1110001 7
b10000110 E
1#
#2760000
0#
#2770000
b10000111 E
b1110010 7
1#
#2780000
0#
#2790000
b1110011 7
b10001000 E
1#
#2800000
0#
#2810000
b10001001 E
b1110100 7
1#
#2820000
0#
#2830000
b1110101 7
b10001010 E
1#
#2840000
0#
#2850000
b10001011 E
b1110110 7
1#
#2860000
0#
#2870000
b1110111 7
b10001100 E
1#
#2880000
0#
#2890000
b10001101 E
b1111000 7
1#
#2900000
0#
#2910000
b1111001 7
b10001110 E
1#
#2920000
0#
#2930000
b10001111 E
b1111010 7
1#
#2940000
0#
#2950000
b1111011 7
b10010000 E
1#
#2960000
0#
#2970000
b10010001 E
b1111100 7
1#
#2980000
0#
#2990000
b1111101 7
b10010010 E
1#
#3000000
0#
#3010000
b10010011 E
b1111110 7
0:
0&
b111 I
1#
#3020000
0#
#3030000
00
0;
b1111111 7
b10010100 E
1#
#3040000
0#
#3050000
b10010101 E
b10000000 7
1#
#3060000
0#
#3070000
b10000001 7
b10010110 E
1#
#3080000
0#
#3090000
b10010111 E
b10000010 7
1#
#3100000
0#
#3110000
b10000011 7
b10011000 E
1#
#3120000
0#
#3130000
b10011001 E
b10000100 7
1#
#3140000
0#
#3150000
b10000101 7
b10011010 E
1#
#3160000
0#
#3170000
b10011011 E
b10000110 7
1#
#3180000
0#
#3190000
b10000111 7
b10011100 E
1#
#3200000
0#
#3210000
b10011101 E
b10001000 7
1#
#3220000
0#
#3230000
b10001001 7
b10011110 E
1#
#3240000
0#
#3250000
b10011111 E
b10001010 7
1#
#3260000
0#
#3270000
b10001011 7
b10100000 E
1#
#3280000
0#
#3290000
b10100001 E
b10001100 7
1#
#3300000
0#
#3310000
b10001101 7
b10100010 E
1#
#3320000
0#
#3330000
b10100011 E
b10001110 7
1:
1&
b1000 I
1#
#3340000
0#
#3350000
10
1;
b10001111 7
b10100100 E
1#
#3360000
0#
#3370000
b10100101 E
b10010000 7
1#
#3380000
0#
#3390000
b10010001 7
b10100110 E
1#
#3400000
0#
#3410000
b10100111 E
b10010010 7
1#
#3420000
0#
#3430000
b10010011 7
b10101000 E
1#
#3440000
0#
#3450000
b10101001 E
b10010100 7
1#
#3460000
0#
#3470000
b10010101 7
b10101010 E
1#
#3480000
0#
#3490000
b10101011 E
b10010110 7
1#
#3500000
0#
#3510000
b10010111 7
b10101100 E
1#
#3520000
0#
#3530000
b10101101 E
b10011000 7
1#
#3540000
0#
#3550000
b10011001 7
b10101110 E
1#
#3560000
0#
#3570000
b10101111 E
b10011010 7
1#
#3580000
0#
#3590000
b10011011 7
b10110000 E
1#
#3600000
0#
#3610000
b10110001 E
b10011100 7
1#
#3620000
0#
#3630000
b10011101 7
b10110010 E
1#
#3640000
0#
#3650000
b10110011 E
b10011110 7
1#
#3660000
0#
#3670000
b10011111 7
b10110100 E
1#
#3680000
0#
#3690000
b10110101 E
b10100000 7
1#
#3700000
0#
#3710000
b10100001 7
b10110110 E
1#
#3720000
0#
#3730000
b10110111 E
b10100010 7
1#
#3740000
0#
#3750000
b10100011 7
b10111000 E
1#
#3760000
0#
#3770000
b10111001 E
b10100100 7
1#
#3780000
0#
#3790000
b10100101 7
b10111010 E
1#
#3800000
0#
#3810000
b10111011 E
b10100110 7
1#
#3820000
0#
#3830000
b10100111 7
b10111100 E
1#
#3840000
0#
#3850000
b10111101 E
b10101000 7
1#
#3860000
0#
#3870000
b10101001 7
b10111110 E
1#
#3880000
0#
#3890000
b10111111 E
b10101010 7
1#
#3900000
0#
#3910000
b10101011 7
b11000000 E
1#
#3920000
0#
#3930000
b11000001 E
b10101100 7
1#
#3940000
0#
#3950000
b10101101 7
b11000010 E
1#
#3960000
0#
#3970000
b11000011 E
b10101110 7
1#
#3980000
0#
#3990000
b10101111 7
b11000100 E
1#
#4000000
0#
#4010000
b11000101 E
b10110000 7
1#
#4020000
0#
#4030000
b10110001 7
b11000110 E
1#
#4040000
0#
#4050000
b11000111 E
b10110010 7
1#
